{
"count": 20,
"startIndex": 0,
"data": [
{
"thumbnails": [
{
"url": "http://assets1.ignimgs.com/2017/02/09/daily-deals-blogrollwarhammer-1486654404275_compact.png",
"size": "compact",
"width": 306,
"height": 172
},
{
"url": "http://assets1.ignimgs.com/2017/02/09/daily-deals-blogrollwarhammer-1486654404275_medium.png",
"size": "medium",
"width": 466,
"height": 262
},
{
"url": "http://assets1.ignimgs.com/2017/02/09/daily-deals-blogrollwarhammer-1486654404275_large.png",
"size": "large",
"width": 626,
"height": 352
}
],
"metadata": {
"headline": "Daily Deals: Humble Bundle Hooks You Up with Total War: Warhammer for Just $12",
"networks": [
"ign"
],
"state": "published",
"slug": "daily-deals-humble-bundle-hooks-you-up-with-total-war-warhammer-for-just-12",
"subHeadline": "Plus Assassin's Creed Unity for just $1.29, free Xbox Live cash, savings on John Wick 2 tickets and more!",
"publishDate": "2017-02-09T17:35:03+0000",
"articleType": "article"
},
"tags": [
"daily-deals"
]
},
{
"thumbnails": [
{
"url": "http://assets2.ignimgs.com/2016/02/09/best-wireless-headphones-blogrolljpg-19cb15_compact.jpg",
"size": "compact",
"width": 306,
"height": 172
},
{
"url": "http://assets2.ignimgs.com/2016/02/09/best-wireless-headphones-blogrolljpg-19cb15_medium.jpg",
"size": "medium",
"width": 466,
"height": 262
},
{
"url": "http://assets2.ignimgs.com/2016/02/09/best-wireless-headphones-blogrolljpg-19cb15_large.jpg",
"size": "large",
"width": 626,
"height": 352
}
],
"metadata": {
"headline": "Best Wireless Bluetooth Headphones",
"networks": [
"ign"
],
"state": "published",
"slug": "best-wireless-bluetooth-headphones",
"subHeadline": "Ditch the wires with these great sounding and long lasting wireless headphones.",
"publishDate": "2017-02-09T17:33:53+0000",
"articleType": "article"
},
"tags": [
"feature",
"lifestyle",
"audio",
"bluetooth",
"earbuds"
]
},
{
"thumbnails": [
{
"url": "http://assets2.ignimgs.com/2015/06/16/southpark1280jpg-b5783c_compact.jpg",
"size": "compact",
"width": 306,
"height": 172
},
{
"url": "http://assets2.ignimgs.com/2015/06/16/southpark1280jpg-b5783c_medium.jpg",
"size": "medium",
"width": 466,
"height": 262
},
{
"url": "http://assets2.ignimgs.com/2015/06/16/southpark1280jpg-b5783c_large.jpg",
"size": "large",
"width": 626,
"height": 352
}
],
"metadata": {
"headline": "South Park: The Fractured But Whole Delayed Again by Ubisoft",
"networks": [
"ign"
],
"state": "published",
"slug": "south-park-the-fractured-but-whole-delayed-again-by-ubisoft",
"subHeadline": "Weak.",
"publishDate": "2017-02-09T17:33:02+0000",
"articleType": "article"
},
"tags": [
"news",
"game",
"pc",
"ps4",
"rpg"
]
},
{
"thumbnails": [
{
"url": "http://assets1.ignimgs.com/2017/02/09/untitled-9-1486661195709_compact.jpg",
"size": "compact",
"width": 306,
"height": 172
},
{
"url": "http://assets1.ignimgs.com/2017/02/09/untitled-9-1486661195709_medium.jpg",
"size": "medium",
"width": 466,
"height": 262
},
{
"url": "http://assets1.ignimgs.com/2017/02/09/untitled-9-1486661195709_large.jpg",
"size": "large",
"width": 626,
"height": 352
}
],
"metadata": {
"headline": "Grand Theft Auto 4 and All DLC Now Playable on Xbox One",
"networks": [
"ign"
],
"state": "published",
"slug": "grand-theft-auto-4-and-all-dlc-now-playable-on-xbox-one",
"subHeadline": "(Not) New York, (not) New York",
"publishDate": "2017-02-09T17:31:45+0000",
"articleType": "article"
},
"tags": [
"news",
"action",
"adventure",
"game",
"grand-theft-auto-iv"
]
},
{
"thumbnails": [
{
"url": "http://assets1.ignimgs.com/2016/12/30/trollhunters-1280-1483119259938_compact.jpg",
"size": "compact",
"width": 306,
"height": 172
},
{
"url": "http://assets1.ignimgs.com/2016/12/30/trollhunters-1280-1483119259938_medium.jpg",
"size": "medium",
"width": 466,
"height": 262
},
{
"url": "http://assets1.ignimgs.com/2016/12/30/trollhunters-1280-1483119259938_large.jpg",
"size": "large",
"width": 626,
"height": 352
}
],
"metadata": {
"headline": "Netflix's Trollhunters Renewed for Season 2",
"networks": [
"ign"
],
"state": "published",
"slug": "netflixs-trollhunters-renewed-for-season-2",
"subHeadline": "Debuting later this year.",
"publishDate": "2017-02-09T17:25:37+0000",
"articleType": "article"
},
"tags": [
"news",
"animation",
"netflixcom",
"show",
"trollhunters"
]
},
{
"thumbnails": [
{
"url": "http://assets2.ignimgs.com/2016/06/01/rszgallerycomics1920x108020160601bmrebirth-copy571fbdfbd6ea3681568612jpg-65361d_compact.jpg",
"size": "compact",
"width": 306,
"height": 172
},
{
"url": "http://assets2.ignimgs.com/2016/06/01/rszgallerycomics1920x108020160601bmrebirth-copy571fbdfbd6ea3681568612jpg-65361d_medium.jpg",
"size": "medium",
"width": 466,
"height": 262
},
{
"url": "http://assets2.ignimgs.com/2016/06/01/rszgallerycomics1920x108020160601bmrebirth-copy571fbdfbd6ea3681568612jpg-65361d_large.jpg",
"size": "large",
"width": 626,
"height": 352
}
],
"metadata": {
"headline": "Justice League vs. Suicide Squad Finale Recap",
"networks": [
"ign"
],
"state": "published",
"slug": "justice-league-vs-suicide-squad-finale-recap",
"publishDate": "2017-02-09T17:00:16+0000",
"articleType": "article",
"subHeadline": "Spoilers! Batman does something quite rare in the final chapter to DC's big event."
},
"tags": []
},
{
"thumbnails": [
{
"url": "http://assets1.ignimgs.com/2017/02/09/ignfirst-injustice2-deadshot-1280-1486601866576_compact.jpg",
"size": "compact",
"width": 306,
"height": 172
},
{
"url": "http://assets1.ignimgs.com/2017/02/09/ignfirst-injustice2-deadshot-1280-1486601866576_medium.jpg",
"size": "medium",
"width": 466,
"height": 262
},
{
"url": "http://assets1.ignimgs.com/2017/02/09/ignfirst-injustice2-deadshot-1280-1486601866576_large.jpg",
"size": "large",
"width": 626,
"height": 352
}
],
"metadata": {
"headline": "6 Things That Make Injustice 2 a New Game -- IGN First",
"networks": [
"ign"
],
"state": "published",
"slug": "6-things-that-make-injustice-2-a-new-game-ign-first",
"subHeadline": "More than just new moves and characters.",
"publishDate": "2017-02-09T17:00:16+0000",
"articleType": "article"
},
"tags": [
"feature",
"fighting",
"game",
"injustice-2",
"netherrealm-studios"
]
},
{
"thumbnails": [
{
"url": "http://assets1.ignimgs.com/2017/02/09/untitled-9-1486658233353_compact.jpg",
"size": "compact",
"width": 306,
"height": 172
},
{
"url": "http://assets1.ignimgs.com/2017/02/09/untitled-9-1486658233353_medium.jpg",
"size": "medium",
"width": 466,
"height": 262
},
{
"url": "http://assets1.ignimgs.com/2017/02/09/untitled-9-1486658233353_large.jpg",
"size": "large",
"width": 626,
"height": 352
}
],
"metadata": {
"headline": "Survive Call of Cthulhu by Slowing Down and Understanding Your World",
"networks": [
"ign"
],
"state": "published",
"slug": "survive-call-of-cthulhu-by-slowing-down-and-understanding-your-world",
"subHeadline": "Needs love and craft.",
"publishDate": "2017-02-09T16:52:29+0000",
"articleType": "article"
},
"tags": [
"preview",
"adventure",
"call-of-cthulhu",
"focus-home-interactive",
"frogwares"
]
},
{
"thumbnails": [
{
"url": "http://assets1.ignimgs.com/2017/02/09/bone-shaker-blog-1486655694515_compact.jpg",
"size": "compact",
"width": 306,
"height": 172
},
{
"url": "http://assets1.ignimgs.com/2017/02/09/bone-shaker-blog-1486655694515_medium.jpg",
"size": "medium",
"width": 466,
"height": 262
},
{
"url": "http://assets1.ignimgs.com/2017/02/09/bone-shaker-blog-1486655694515_large.jpg",
"size": "large",
"width": 626,
"height": 352
}
],
"metadata": {
"headline": "Rocket League Announces Hot Wheels DLC",
"networks": [
"ign"
],
"state": "published",
"slug": "rocket-league-announces-hot-wheels-dlc",
"subHeadline": "Two Hot Wheels battle cars are coming February 21.",
"publishDate": "2017-02-09T16:24:02+0000",
"articleType": "article"
},
"tags": [
"news",
"action",
"game",
"pc",
"ps4"
]
},
{
"thumbnails": [
{
"url": "http://assets1.ignimgs.com/2017/02/09/untitled-9-1486657296159_compact.jpg",
"size": "compact",
"width": 306,
"height": 172
},
{
"url": "http://assets1.ignimgs.com/2017/02/09/untitled-9-1486657296159_medium.jpg",
"size": "medium",
"width": 466,
"height": 262
},
{
"url": "http://assets1.ignimgs.com/2017/02/09/untitled-9-1486657296159_large.jpg",
"size": "large",
"width": 626,
"height": 352
}
],
"metadata": {
"headline": "Street Fighter 5's Latest Character, Kolin Revealed",
"networks": [
"ign"
],
"state": "published",
"slug": "street-fighter-5s-latest-character-kolin-revealed",
"publishDate": "2017-02-09T16:21:21+0000",
"articleType": "article",
"subHeadline": "The fans were right - an ice-attacking character from SFV's story mode will join the fray this month."
},
"tags": [
"news",
"game",
"street-fighter-v",
"ps4",
"capcom"
]
},
{
"thumbnails": [
{
"url": "http://assets1.ignimgs.com/2017/02/04/legobatmanmovie-1280-2-1486205402178_compact.jpg",
"size": "compact",
"width": 306,
"height": 172
},
{
"url": "http://assets1.ignimgs.com/2017/02/04/legobatmanmovie-1280-2-1486205402178_medium.jpg",
"size": "medium",
"width": 466,
"height": 262
},
{
"url": "http://assets1.ignimgs.com/2017/02/04/legobatmanmovie-1280-2-1486205402178_large.jpg",
"size": "large",
"width": 626,
"height": 352
}
],
"metadata": {
"headline": "The LEGO Batman Movie Review",
"networks": [
"ign"
],
"state": "published",
"slug": "the-lego-batman-movie-review-2",
"publishDate": "2017-02-09T16:00:03+0000",
"articleType": "article",
"subHeadline": "The Dark Knight battles the Joker while learning how to be a part of a family in this amusing, anarchic take on the hero."
},
"tags": []
},
{
"thumbnails": [
{
"url": "http://assets2.ignimgs.com/2015/05/18/loboblogrolljpg-9b63f6_compact.jpg",
"size": "compact",
"width": 306,
"height": 172
},
{
"url": "http://assets2.ignimgs.com/2015/05/18/loboblogrolljpg-9b63f6_medium.jpg",
"size": "medium",
"width": 466,
"height": 262
},
{
"url": "http://assets2.ignimgs.com/2015/05/18/loboblogrolljpg-9b63f6_large.jpg",
"size": "large",
"width": 626,
"height": 352
}
],
"metadata": {
"headline": "Comic Book Reviews for February 8, 2017",
"networks": [
"ign"
],
"state": "published",
"slug": "comic-book-reviews-for-february-8-2017",
"subHeadline": "The Justice League are keeping busy.",
"publishDate": "2017-02-09T15:01:19+0000",
"articleType": "article"
},
"tags": [
"feature",
"company",
"dc-comics",
"marvel-comics",
"image-comics"
]
},
{
"thumbnails": [
{
"url": "http://assets1.ignimgs.com/2017/02/09/castlevania3-1280-1486599507410_compact.jpg",
"size": "compact",
"width": 306,
"height": 172
},
{
"url": "http://assets1.ignimgs.com/2017/02/09/castlevania3-1280-1486599507410_medium.jpg",
"size": "medium",
"width": 466,
"height": 262
},
{
"url": "http://assets1.ignimgs.com/2017/02/09/castlevania3-1280-1486599507410_large.jpg",
"size": "large",
"width": 626,
"height": 352
}
],
"metadata": {
"headline": "Netflix Castlevania Animated Series Aiming to Be 'R-Rated as F***'",
"networks": [
"ign"
],
"state": "published",
"slug": "netflix-animated-series-aiming-to-be-r-rated-as-f",
"publishDate": "2017-02-09T15:00:48+0000",
"articleType": "article",
"subHeadline": "Producer Adi Shankar confirmed the Netflix series isn't looking to undercut the game franchise's level of violence."
},
"tags": []
},
{
"thumbnails": [
{
"url": "http://assets1.ignimgs.com/2017/02/09/for-honor-blogroll-1486642952314_compact.jpg",
"size": "compact",
"width": 306,
"height": 172
},
{
"url": "http://assets1.ignimgs.com/2017/02/09/for-honor-blogroll-1486642952314_medium.jpg",
"size": "medium",
"width": 466,
"height": 262
},
{
"url": "http://assets1.ignimgs.com/2017/02/09/for-honor-blogroll-1486642952314_large.jpg",
"size": "large",
"width": 626,
"height": 352
}
],
"metadata": {
"headline": "For Honor: Where to Preorder in the UK",
"networks": [
"ign"
],
"state": "published",
"slug": "for-honor-where-to-preorder-in-the-uk",
"subHeadline": "Find where the best place to preorder For Honor below.",
"publishDate": "2017-02-09T14:20:43+0000",
"articleType": "article"
},
"tags": [
"news",
"action",
"for-honor",
"game",
"pc"
]
},
{
"thumbnails": [
{
"url": "http://assets1.ignimgs.com/2017/02/09/sf5-1486646621777_compact.jpg",
"size": "compact",
"width": 306,
"height": 172
},
{
"url": "http://assets1.ignimgs.com/2017/02/09/sf5-1486646621777_medium.jpg",
"size": "medium",
"width": 466,
"height": 262
},
{
"url": "http://assets1.ignimgs.com/2017/02/09/sf5-1486646621777_large.jpg",
"size": "large",
"width": 626,
"height": 352
}
],
"metadata": {
"headline": "Street Fighter 5 Character Reveal Coming Soon - and Fans Think They Know Who It Is",
"networks": [
"ign"
],
"state": "published",
"slug": "street-fighter-5-character-reveal-coming-soon-and-fans-think-they-know-who-it-is",
"subHeadline": "UPDATE: The fans were right - it's Kolin.",
"publishDate": "2017-02-09T14:10:58+0000",
"articleType": "article"
},
"tags": [
"news",
"capcom",
"fighting",
"game",
"pc"
]
},
{
"thumbnails": [
{
"url": "http://assets1.ignimgs.com/2017/01/04/n7-1483551968691_compact.jpg",
"size": "compact",
"width": 306,
"height": 172
},
{
"url": "http://assets1.ignimgs.com/2017/01/04/n7-1483551968691_medium.jpg",
"size": "medium",
"width": 466,
"height": 262
},
{
"url": "http://assets1.ignimgs.com/2017/01/04/n7-1483551968691_large.jpg",
"size": "large",
"width": 626,
"height": 352
}
],
"metadata": {
"headline": "Mass Effect: Andromeda Removed Paragon/Renegade System to Allow for Old-School Role-Playing",
"networks": [
"ign"
],
"state": "published",
"slug": "mass-effect-andromeda-removed-paragonrenegade-system-to-allow-for-old-school-role-playing",
"subHeadline": "Shepard-ed away.",
"publishDate": "2017-02-09T14:06:52+0000",
"articleType": "article"
},
"tags": [
"news",
"bioware",
"electronic-arts",
"game",
"mass-effect-andromeda"
]
},
{
"thumbnails": [
{
"url": "http://assets1.ignimgs.com/2017/02/09/group-j-tengu-battel02-1484301724-1486645126689_compact.jpg",
"size": "compact",
"width": 306,
"height": 172
},
{
"url": "http://assets1.ignimgs.com/2017/02/09/group-j-tengu-battel02-1484301724-1486645126689_medium.jpg",
"size": "medium",
"width": 466,
"height": 262
},
{
"url": "http://assets1.ignimgs.com/2017/02/09/group-j-tengu-battel02-1484301724-1486645126689_large.jpg",
"size": "large",
"width": 626,
"height": 352
}
],
"metadata": {
"headline": "Nioh Co-op Changed in Final Game Because It Was \"Too Easy\"",
"networks": [
"ign"
],
"state": "published",
"slug": "nioh-co-op-changed-in-final-game-because-it-was-too-easy",
"subHeadline": "Nioh no-no.",
"publishDate": "2017-02-09T12:59:44+0000",
"articleType": "article"
},
"tags": [
"news",
"action",
"game",
"nioh",
"ps4"
]
},
{
"thumbnails": [
{
"url": "http://assets1.ignimgs.com/2015/06/25/falloutshelterjpg-22eb5a_compact.jpg",
"size": "compact",
"width": 306,
"height": 172
},
{
"url": "http://assets1.ignimgs.com/2015/06/25/falloutshelterjpg-22eb5a_medium.jpg",
"size": "medium",
"width": 466,
"height": 262
},
{
"url": "http://assets1.ignimgs.com/2015/06/25/falloutshelterjpg-22eb5a_large.jpg",
"size": "large",
"width": 626,
"height": 352
}
],
"metadata": {
"headline": "Just Because Fallout Shelter Hit Xbox Doesn't Mean It'll Come to PS4",
"networks": [
"ign"
],
"state": "published",
"slug": "just-because-fallout-shelter-hit-xbox-doesnt-mean-itll-come-to-ps4",
"subHeadline": "Not yet nuked.",
"publishDate": "2017-02-09T12:34:51+0000",
"articleType": "article"
},
"tags": [
"news",
"android",
"bethesda-game-studios",
"bethesda-softworks",
"fallout-shelter"
]
},
{
"thumbnails": [
{
"url": "http://assets1.ignimgs.com/2017/02/09/image-1486616899137_compact.jpeg",
"size": "compact",
"width": 306,
"height": 172
},
{
"url": "http://assets1.ignimgs.com/2017/02/09/image-1486616899137_medium.jpeg",
"size": "medium",
"width": 466,
"height": 262
},
{
"url": "http://assets1.ignimgs.com/2017/02/09/image-1486616899137_large.jpeg",
"size": "large",
"width": 626,
"height": 352
}
],
"metadata": {
"headline": "Justice League/ Mighty Morphin Power Rangers #2 Review",
"networks": [
"ign"
],
"state": "published",
"slug": "justice-league-mighty-morphin-power-rangers-2-review",
"subHeadline": "Zedd ahead.",
"publishDate": "2017-02-09T05:20:55+0000",
"articleType": "article"
},
"tags": [
"review",
"book",
"dc-comics",
"justice-leaguemighty-morphin-power-rangers-2",
"print"
]
},
{
"thumbnails": [
{
"url": "http://assets1.ignimgs.com/2017/02/08/millllunnamed-1486582839404_compact.jpg",
"size": "compact",
"width": 306,
"height": 172
},
{
"url": "http://assets1.ignimgs.com/2017/02/08/millllunnamed-1486582839404_medium.jpg",
"size": "medium",
"width": 466,
"height": 262
},
{
"url": "http://assets1.ignimgs.com/2017/02/08/millllunnamed-1486582839404_large.jpg",
"size": "large",
"width": 626,
"height": 352
}
],
"metadata": {
"headline": "The Expanse: \"Static\" Review",
"networks": [
"ign"
],
"state": "published",
"slug": "the-expanse-static-review",
"subHeadline": "\"You keep picking fights with the wrong people.\"",
"publishDate": "2017-02-09T03:59:50+0000",
"articleType": "article"
},
"tags": [
"review",
"episode",
"static-the-expanse",
"the-expanse",
"tv-review"
]
}
]
}